<Properties StartupConfiguration="{F0BAF7FA-9067-47A5-9744-FCC56BDE9306}|Default">
  <MonoDevelop.Ide.DebuggingService.Breakpoints>
    <BreakpointStore />
  </MonoDevelop.Ide.DebuggingService.Breakpoints>
  <Xamarin.Addins.Core.Project ActiveDebugTarget="MonoDevelop.IPhone.IPhoneDeviceTarget" />
  <MonoDevelop.Ide.Workbench ActiveDocument="win_programming_try/MainPage.xaml">
    <Files>
      <File FileName="win_programming_try/MainPage.xaml.cs" />
      <File FileName="win_programming_try/MainPage.xaml" Line="15" Column="8" />
    </Files>
    <Pads>
      <Pad Id="ProjectPad">
        <State name="__root__">
          <Node name="win_programming_try" expanded="True">
            <Node name="win_programming_try" expanded="True">
              <Node name="Dependencies" selected="True" />
              <Node name="MainPage.xaml" expanded="True" />
            </Node>
          </Node>
        </State>
      </Pad>
    </Pads>
  </MonoDevelop.Ide.Workbench>
  <MonoDevelop.Ide.Workspace ActiveConfiguration="Debug" />
  <MultiItemStartupConfigurations />
  <MonoDevelop.Ide.DebuggingService.PinnedWatches />
  <MonoDevelop.Ide.ItemProperties.win__programming__try PreferredExecutionTarget="MonoDevelop.IPhone.IPhoneDeviceTarget" />
</Properties>